poetry_example_project/__init__.py
poetry_example_project/hello.py
poetry_example_project/tools/__init__.py
poetry_example_project/tools/hellotools.py
poetry_example_project-0.1.1.dist-info/LICENSE
poetry_example_project-0.1.1.dist-info/METADATA
poetry_example_project-0.1.1.dist-info/WHEEL
poetry_example_project-0.1.1.dist-info/RECORD
