Metadata-Version: 2.1
Name: poetry-example-project
Version: 0.1.1
Summary: Mon exemple de projet utilisant Poetry
Author: Jules
Author-email: 32939951+jdnob@users.noreply.github.com
Requires-Python: >=3.10,<4.0
Classifier: Programming Language :: Python :: 3
Classifier: Programming Language :: Python :: 3.10
Classifier: Programming Language :: Python :: 3.11
Requires-Dist: mock (>=5.0.1,<6.0.0)
Requires-Dist: oauthlib (==3.1.0)
Requires-Dist: pika (==1.2.1)
Requires-Dist: pytest (>=7.2.2,<8.0.0)
Requires-Dist: pytest-mock (>=3.10.0,<4.0.0)
Requires-Dist: requests (==2.25.1)
Requires-Dist: requests-oauthlib (==1.3.0)
